pyplexos/__init__.py
pyplexos-0.1.1.dist-info/METADATA
pyplexos-0.1.1.dist-info/WHEEL
pyplexos-0.1.1.dist-info/RECORD
